odoo/addons/account_move_line_check_number/README.rst
odoo/addons/account_move_line_check_number/__init__.py
odoo/addons/account_move_line_check_number/__manifest__.py
odoo/addons/account_move_line_check_number/i18n/account_move_line_check_number.pot
odoo/addons/account_move_line_check_number/i18n/es.po
odoo/addons/account_move_line_check_number/i18n/it.po
odoo/addons/account_move_line_check_number/models/__init__.py
odoo/addons/account_move_line_check_number/models/account_move.py
odoo/addons/account_move_line_check_number/readme/CONTRIBUTORS.rst
odoo/addons/account_move_line_check_number/readme/DESCRIPTION.rst
odoo/addons/account_move_line_check_number/static/description/icon.png
odoo/addons/account_move_line_check_number/static/description/index.html
odoo/addons/account_move_line_check_number/views/account_move_views.xml
odoo14_addon_account_move_line_check_number-14.0.1.0.1.dev8.dist-info/METADATA
odoo14_addon_account_move_line_check_number-14.0.1.0.1.dev8.dist-info/WHEEL
odoo14_addon_account_move_line_check_number-14.0.1.0.1.dev8.dist-info/top_level.txt
odoo14_addon_account_move_line_check_number-14.0.1.0.1.dev8.dist-info/RECORD
